PyGeneticCode.cpython-312-x86_64-linux-gnu.so
pygenetic_code/__init__.py
pygenetic_code/_version.py
pygenetic_code/cli.py
pygenetic_code/code_to_table.py
pygenetic_code/dna_and_rna.py
pygenetic_code/encode_codons.py
pygenetic_code/error.py
pygenetic_code/genetic_code.py
pygenetic_code/ncbi_table_to_json.py
pygenetic_code/print_codes.py
pygenetic_code/translations.py
pygenetic_code/version.py
pygenetic_code-0.20.0.dist-info/METADATA
pygenetic_code-0.20.0.dist-info/WHEEL
pygenetic_code-0.20.0.dist-info/entry_points.txt
pygenetic_code-0.20.0.dist-info/licenses/LICENSE
pygenetic_code-0.20.0.dist-info/RECORD
