Metadata-Version: 2.1
Name: pygenetic_code
Version: 0.20.0
Summary: Translate DNA sequences to protein sequences using different genetic codes and translation tables
Author-Email: Rob Edwards <raedwards@gmail.com>
Maintainer-Email: Rob Edwards <raedwards@gmail.com>
Classifier: Environment :: Console
Classifier: Environment :: MacOS X
Classifier: Intended Audience :: Science/Research
Classifier: License :: OSI Approved :: MIT License
Classifier: Natural Language :: English
Classifier: Operating System :: POSIX :: Linux
Classifier: Programming Language :: Python :: 3.10
Classifier: Programming Language :: Python :: 3.11
Classifier: Programming Language :: Python :: 3.12
Classifier: Programming Language :: C
Classifier: Topic :: Scientific/Engineering :: Bio-Informatics
License-File: LICENSE
